mlflow_vizmod/styles/altair.py
mlflow_vizmod.styles.altair-1.1.2.dist-info/LICENSE
mlflow_vizmod.styles.altair-1.1.2.dist-info/METADATA
mlflow_vizmod.styles.altair-1.1.2.dist-info/WHEEL
mlflow_vizmod.styles.altair-1.1.2.dist-info/entry_points.txt
mlflow_vizmod.styles.altair-1.1.2.dist-info/top_level.txt
mlflow_vizmod.styles.altair-1.1.2.dist-info/RECORD
